[
  {
    "start": 1778977140,
    "end": 1778978460,
    "name": "בובספוג 4 (מתורגם) פרק 71",
    "description": "אנימציה. פרק 71 פרל חוגגת את יום הולדתה ה-16 ומר קראב חייב לעשות הכל כדי שהמסיבה תהיה מושלמת. בובספוג מקבל מברק ובו נאמר כי הוא מלך הקראטה. סנדי חושבת שמשהו חשוד ויוצאת איתו לטקס ההכתרה. כ' עב'. (שח)"
  },
  {
    "start": 1778978460,
    "end": 1778979840,
    "name": "בובספוג 4 (מתורגם) פרק 72",
    "description": "אנימציה. פרק 72 המרית של בובספוג נשברת ובזמן שהישנה שוכבת לה בבית החולים עליו להחליט אם לקנות חדשה. בובספוג חופר משאלות עבור מר קראב כדי להכניס עוד כסף. כ' עב'. (שח)"
  },
  {
    "start": 1778979840,
    "end": 1778981220,
    "name": "בובספוג 3 (מתורגם) פרק 42",
    "description": "סקווידוויד מתעקש להצטרף למועדון של בובספוג ופטריק וכך השלושה מוצאים את עצמם אבודים ביער אצות; בובספוג מצליח לאלף סוסת ים פראית אבל מר קראב דורש ממנו להיפטר ממנה. (שח)"
  },
  {
    "start": 1778981220,
    "end": 1778982540,
    "name": "בובספוג 3 (מתורגם) פרק 43",
    "description": "בובספוג נדהם לגלות שסקווידוורד מעולם לא טעם קציצת סרטן. הוא מצליח לשכנע אותו לקחת ביס אחד וסקווידוורד מגלה להפתעתו שזה טעים מאוד. הוא לא מודה בכך בפני בובספוג אבל אחר כך מנסה להשיג קציצה נוספת. (שח)"
  },
  {
    "start": 1778982540,
    "end": 1778983920,
    "name": "בובספוג 3 (מתורגם) פרק 44",
    "description": "מפקח בריאות מגיע ל''סרטן הפריך'' ובובספוג ומר קראב מנסים לרצות אותו. כשהם חושבים שמדובר במתחזה הם מחליטים להתנכל לו והם מכינים לו קציצה מסריחה במיוחד שחונקת אותו. (שח)"
  },
  {
    "start": 1778983920,
    "end": 1778985300,
    "name": "בובספוג 1 (מתורגם) פרק 2",
    "description": "אנימציה. פרק 2 בובספוג ופטריק פותחים דוכן להפרחת בועות ומצליחים לשכנע את מר קארב לנסות להפריח בועות. בובספוג מגלה שבכל פעם שמכנסיו נקרעים כולם צוחקים וזה מוצא חן בעיניו. כ' עב'. (שח)"
  },
  {
    "start": 1778985300,
    "end": 1778986800,
    "name": "בובספוג 1 (מתורגם) פרק 3",
    "description": "מצויר. פרק 3 בובספוג ופטריק מזמינים את מר תמנון לצאת לדיג מדוזות. כשנדמה שהמצב לא יכול להיות גרוע יותר, זה בדיוק מה שקורה ופלנקטון מנסה לגנוב את הנוסחה הסודית של קציצת הסרטן. כ' עב'. (שח)"
  },
  {
    "start": 1778986800,
    "end": 1778988240,
    "name": "נעלמים 2 פרק 61",
    "description": "נוער. פרק 61. הבנות מארגנות מסיבת פיג'מות, ביקור במשתלה ומאיפה מגיעה החריקה? (שח)"
  },
  {
    "start": 1778988240,
    "end": 1778989680,
    "name": "נעלמים 2 פרק 62",
    "description": "נוער. פרק 62. הקרמבו שלא נגמר, דניאלה ודולב עושים הצגה ומתי נולד דני קושמרו? (שח)"
  },
  {
    "start": 1778989680,
    "end": 1778991120,
    "name": "הסוכן פרק 9",
    "description": "דברת ורזי משתפים פעולה באופן נדיר כשהם מייצרים זוגיות יח''צ מתוקשרת לסוקי וקים. באופן מפתיע הזוגיות המומצאת פועלת טוב מהצפוי, כמו גם שיתוף הפעולה של רזי ודברת. כ' עב'. (שח)"
  },
  {
    "start": 1778991120,
    "end": 1778992440,
    "name": "הסוכן פרק 10",
    "description": "בדיוק בשנייה בה אמור לצאת לקים שיר חדש ומבריק, רזי מגלה שסוקי הוציא בדיוק את אותו השיר עם אותו הלחן. עכשיו אין לו ספק - יש בסוכנות מדליף, והוא הולך למצוא אותו בכל מחיר. כ' עב'. (שח)"
  },
  {
    "start": 1778992440,
    "end": 1778993820,
    "name": "אבא מטפלת 4 פרק 11",
    "description": "אחרי שרואה את אביה בדכאון, שקד גורמת לאייל לחשוב שהוא המציא המצאה משמעותית ששינתה את העולם. היא לא יודעת במה היא מסתבכת, במקביל אלינור חושדת שדופק מסתיר ממנה סודות. כ' עב'. (שח)"
  },
  {
    "start": 1778993820,
    "end": 1778995260,
    "name": "אבא מטפלת 4 פרק 12",
    "description": "לילי מגלה שמיקי מעולם לא חגגה בת מצווה ומחליטה לתקן את העוול ההיסטורי, במקביל שאר בני משפחת דנינו מגלים פרט מוזר ומדהים על אמם. (אורחת אגם בוחבוט). (שח)"
  },
  {
    "start": 1778995260,
    "end": 1778996760,
    "name": "צייר המערות, חדש! פרק 11",
    "description": "אובו יוצא לדייט, אבל בוגה בטוחה שזו בעצם מלכודת ומחליטה לעקוב אחריו. בבה מבלה יותר ויותר זמן עם ביף. יותר מדי אם אתם שואלים אותי. כ' עב'. (שח)"
  },
  {
    "start": 1778996760,
    "end": 1778998200,
    "name": "צייר המערות, חדש! פרק 12",
    "description": "רוצים לדעת איך באים ילדים לעולם? גם פו! מיקה מנסה למכור לה איזה סיפור, אבל את פו לא קונה את זה ויוצאת לחקירה. חוץ מזה, גם אובו מסתבך בשקרים, ולומד ששקרים הורסים יחסים. כ' עב'. (שח)"
  },
  {
    "start": 1778998200,
    "end": 1778999760,
    "name": "יונייטד היי",
    "description": "לבנה נקש מנסה בכל דרך להגיע אל ליבה של ניקול. נסיך מונקו מגלה שהבן שלו מאוהב בילדה ישראלית בשם דני והוא זועם. רותם מקבל מעלמה הצעה שאי אפשר לסרב לה. כ' עב'. (שח)"
  },
  {
    "start": 1778999760,
    "end": 1779001320,
    "name": "יונייטד היי פרק 14",
    "description": "ניקול עומדת מול אמא שלה. עומר מגיע לפגוש את רודריגו ומנצל אותו. ונסה חוזרת, אבל לא כולם שמחים. עלמה שולחת את רותם למשימה חדשה. דני נשברת כשהיא מגלה את השקר הגדול, ואת העובדה שהיא עומדת לשלם את המחיר. (שח)"
  },
  {
    "start": 1779001320,
    "end": 1779002700,
    "name": "ספיידרז 2 פרק 254",
    "description": "דניאל אנה ונוח יוצאים לשמורה לחפש אחר הססמונטור. בארי חוקר את אמילי. ניקי ושון מנסים לברוח מהמועצה, אך נתקלים במכשול לא צפוי. גיל שולח את ליאם למשימה מסוכנת. (שח)"
  },
  {
    "start": 1779002700,
    "end": 1779004260,
    "name": "ספיידרז 2 פרק 256",
    "description": "ליאם מתלבט אם לעזור לפישרים. אמילי מאוכזבת שלא הצליחה לעזור לגאיה. ארנסטו מתעקש להמשיך במשימה כנגד כל הסיכויים. ניקי ואנה מהנדסות מבצע נועז כדי לתפוס את ארנסטו במקום מפתיע. כ' עב'. (שח)"
  },
  {
    "start": 1779004260,
    "end": 1779005640,
    "name": "פול ספיד 2, חדש! פרק 2",
    "description": "הדמות המסתורית חומקת ברגע האחרון. נמרוד נחרד כשפושע מקומי מופיע, ועומר מגלה סוד שמייקי מסתיר. החבורה חוגגת בבריכה עד שחבורת פושעים גורמת לנזק לאופנועים ומאיימת על נמרוד. כ' עב'. (שח)"
  },
  {
    "start": 1779005640,
    "end": 1779007260,
    "name": "פול ספיד 2, חדש! פרק 3",
    "description": "נמרוד מגלה למאור את הסוד שהסתיר לגבי המלון. פרגוז'ין לוחץ את נמרוד לפינה ומאור מתנדב לעזור. עמליה מנסה להתקרב למאור, ונועה מגלה שהוא הלווה את כל כספו לנמרוד. כ' עב'. (שח)"
  },
  {
    "start": 1779007260,
    "end": 1779008880,
    "name": "אבא מטפלת פרק 12",
    "description": "ציור שלילי מציירת בשביל אורי לתחרות כיתתית מצליח קצת הרבה יותר מדי וגורם לשרשרת תקלות בלתי צפויות. במקביל אלינור מגלה שאבא שלה לא אוהב את יודפת אהובה. היא תעשה הכול כדי לשנות את זה. (שח)"
  },
  {
    "start": 1779008880,
    "end": 1779010560,
    "name": "אבא מטפלת פרק 13",
    "description": "לילי עוזרת לאורי להילחם בתופעת הבריונות בבית ספרו בדרכיה היחודיות וכתוצאה מכך מסבכת אותו ואת שקד להרפתקה אחת יותר מדי, במקביל ליאור חווה חוויה מסעירה שמובילה אותו להחלטות מרעישות. (שח)"
  },
  {
    "start": 1779010560,
    "end": 1779012060,
    "name": "יונייטד היי פרק 1",
    "description": "ברוכים הבאים לתיכון הכי יוקרתי בארץ ובעולם, שלא כל אחד יכול להתקבל אליו. אז איך זה יכול להיות שבת של נהג ובן של נסיך יצליחו להסתיר את זהותם האמיתית, לעבוד על כולם ולהתחיל את שנת הלימודים ביחד? כ' עב'. (שח)"
  },
  {
    "start": 1779012060,
    "end": 1779013620,
    "name": "יונייטד היי פרק 2",
    "description": "רגע אחרי פיצוץ המזוודה של רפאל, גם דני מתפוצצת על רפאל והוא דווקא נהנה מזה. כולם מחפשים את ונסה שברחה. התלמידים מחולקים לחדרים ולא כולם אוהבים את השיבוץ שקיבלו. ואצל מי נמצאת טבעת החותם המלכותי? כ' עב (שח)"
  },
  {
    "start": 1779013620,
    "end": 1779015000,
    "name": "קווסט פרק 10",
    "description": "האמת על דוד מתגלה ושוברת את גאיה. אבשה מנסה לשחרר את אבא שלו. רייבן ונגה עומדות לחשוף את גורי ולירז ואדם עומד לחשוף את מאי. כ' עב'. (שח)"
  },
  {
    "start": 1779015000,
    "end": 1779016440,
    "name": "קווסט פרק 11",
    "description": "מבצע השחרור של המכרה יוצא לדרך וסופו המפתיע משאיר את כולם המומים. נגה מתמודדת עם השלכות הכישלון, מאי חוגגת את ניצחונה ורק גורי מרגיש רע עם השקר שלהם. כ' עב'. (שח)"
  },
  {
    "start": 1779016440,
    "end": 1779017880,
    "name": "נעלמים 3 פרק 23",
    "description": "נוער. פרק 23. (שח)"
  },
  {
    "start": 1779017880,
    "end": 1779019380,
    "name": "נעלמים 3 פרק 24",
    "description": "נוער. פרק 24. (שח)"
  },
  {
    "start": 1779019380,
    "end": 1779020880,
    "name": "פול ספיד 2, חדש! פרק 17",
    "description": "חבורה נתקלת בשטרות מזויפים, ופריגוז'ין לא מהסס להשתמש בנחש כדי להפעיל עליהם לחץ למצוא את הכסף האמיתי. *הסדרה מכילה תכנים רגישים הקשורים בהתמכרויות, במטרה להעלות מודעות לנושא זה. כ' עב'. (שח)"
  },
  {
    "start": 1779020880,
    "end": 1779022380,
    "name": "פול ספיד 2, חדש! פרק 18",
    "description": "החבורה מגלה מי גנב את הכסף. האם יספיקו להציל את נמרוד לפני שיהיה מאוחר מדי? ההרפתקה הבלתי נשכחת מגיעה לסיום עוצר נשימה. *הסדרה מכילה תכנים רגישים הקשורים בהתמכרויות במטרה להעלות מודעות לנושא זה. כ' עב (שח)"
  },
  {
    "start": 1779022380,
    "end": 1779023820,
    "name": "אבא מטפלת 6 פרק 5",
    "description": "הזמר האלוהי מני קלמארי נרצח ברחבי הדונאטסיה, וכולם כולל כולם חשודים במעשה. (אורח שחר טבוך). כ' עב'. (שח)"
  },
  {
    "start": 1779023820,
    "end": 1779025200,
    "name": "אבא מטפלת 6 פרק 6",
    "description": "לילי סיירוס נוספת צצה בדונאטסיה דווקא ביום ששקד מצפה לדייט חשוב עם חבר אמריקאי מסתורי. מיקי יוצאת לחפש אוצר משפחתי עתיק יומין. כ' עב'. (שח)"
  },
  {
    "start": 1779025200,
    "end": 1779026700,
    "name": "יונייטד היי פרק 11",
    "description": "ליה מרגישה אשמה במה שקרה לוונסה, ורותם משתגע מרוב דאגה אליה. רודריגו חושף את הקשר בינו לבין עומר. נסיך מונקו דורש שיורש העצר יחזור הביתה מיד. כ' עב'. (שח)"
  },
  {
    "start": 1779026700,
    "end": 1779028260,
    "name": "יונייטד היי פרק 12",
    "description": "דני מתקשה להשלים עם הפרידה מרפאל ולא יודעת שיש לו תוכניות אחרות. ונסה מקבלת בשורות רעות ואורח מפתיע. עלמה מופתעת לגלות שהיא פוטרה לא רק מיונייטד היי. עומר מציע ללירז ולאגם פתרון שיציל אותם. כ' עב'. (שח)"
  },
  {
    "start": 1779028260,
    "end": 1779029940,
    "name": "פול ספיד פרק 21",
    "description": "עומר מבקרת את מייקי בבית החולים והשניים מתקרבים. החוקרים מוצאים פריט חשוד בלוקר של לוקא. ראיית הזהב נחשפת והפושע שחיבל באופנוע מתגלה. כ' עב'. (שח)"
  },
  {
    "start": 1779029940,
    "end": 1779031740,
    "name": "פול ספיד פרק 22",
    "description": "פרק סיום העונה! הגמר הגדול. החוקרים חייבים לתפוס את הפושע לפני שיפגע ברוכב נוסף. מי תהיה הנבחרת המנצחת בגמר הגדול, ומי יזכה בתחרות האישית. כ' עב'. (שח)"
  },
  {
    "start": 1779031740,
    "end": 1779033240,
    "name": "אבא מטפלת 6 פרק 19",
    "description": "בר ומיקי נסחפות לטלנובלה המגוחכת ''לוסליטה ממסיטה'' ומתחילות להתבלבל בין מציאות לדמיון. אייל מנסה להגדיל את מספר העוקבים של שקד בכל דרך אפשרית. כ' עב'. (שח)"
  },
  {
    "start": 1779033240,
    "end": 1779034740,
    "name": "אבא מטפלת 6 פרק 20",
    "description": "אלינור מארחת את הדמויות בסדרה לערב נוצץ של העלאת זכרונות והצגת כשרונות שאיש לא הכיר. כ' עב' (שח)"
  },
  {
    "start": 1779034740,
    "end": 1779036240,
    "name": "ספיידרז",
    "description": "ההורים מגלים על הספיידרז, אך מסרבים לשתף אותם במשימה. השותף של גודמן נפגש עם האופנוענית שייבשה את האגם. טומי מתעמת עם בריון בחוג דרמה. ניקי ושון עושים אימון זוגי. (שח)"
  },
  {
    "start": 1779036240,
    "end": 1779037620,
    "name": "ספיידרז",
    "description": "ניקי מצילה את נוח במשימה שהסתבכה, והוא מחליט לצרף אותה לחקירה. דניאל שומע על כך, ודורש להצטרף גם. שון שם לב שמפלס המים באגם יורד. טומי מתעצבן לגלות שהמשפחה עובדת בלעדיו. (שח)"
  },
  {
    "start": 1779037620,
    "end": 1779039240,
    "name": "אבא מטפלת - שפת הסימנים פרק 4",
    "description": "''קומדיה. עלילת הסדרה עוקבת אחר אייל מנסיני, אב לבת יחידה, שקד, שנאלץ לקטוע את שגרת הבטלה שלו לאחר שידו אינה משגת לקנות לה מתנת יום הולדת. בגיל 40 הוא מחליט למצוא עבודה ולשם כך ממציא את עצמו מחדש (שח)"
  },
  {
    "start": 1779039240,
    "end": 1779040740,
    "name": "פוראבר פרק 15",
    "description": "מספר העוקבים של גל גדות בעלייה חדה. סטיבן ממשיך לנסות להפעיל בעצמו את התא בביוטקס. רומי מספרת לבתיה מה כואב לה. עומר חוטף סטירה מיולי. (שח)"
  },
  {
    "start": 1779040740,
    "end": 1779042240,
    "name": "פוראבר פרק 16",
    "description": "דרמה מוסיקלית. בתיה מספרת לרומי על ההחלטה שלה ולרומי יש הצעה מפתיעה. גל גדות פוגש במסדרונות בית הספר חבר מתקופת התיכון - הזמר דניאל סלומון. עומר מציע ליולי הצעה. כ' עב. (שח)"
  },
  {
    "start": 1779042240,
    "end": 1779043260,
    "name": "בצפר פרק 4",
    "description": "4. אביגיל המזכירה רוצה להחליף את צלצול בית הספר בשיר לבחירת התלמידים, סמדר המורה לספורט רוצה להיות אחת מהחברה ואריה השרת מנסה לתקן את המזגן בצורה פסיכולוגית. (שח)"
  },
  {
    "start": 1779043260,
    "end": 1779044340,
    "name": "בצפר פרק 5",
    "description": "5. אביגיל המזכירה מנסה לגייס כסף על מנת להציל את המסע לפולין שבוטל בגלל בעיות תקציב. מיילי מספר לארקדי על מיזם הכובעסדה. (שח)"
  },
  {
    "start": 1779044340,
    "end": 1779045720,
    "name": "בובספוג 8 פרק 171",
    "description": "אנימציה. פרק 171 קרן מתחילה לעבוד בסרטן הפריך. לבובספוג יש קושי להירדם ואילו פטריק נאבק כדי להישאר ער... כ' עב. (שח)"
  },
  {
    "start": 1779045720,
    "end": 1779047100,
    "name": "בובספוג 8 - 172. פרצוף קפוא/עולם הכפפה ז''ל פרק 172",
    "description": "אנימציה. פרק 172 בובספוג ופטריק עושים פרצופים ומר קראב מספר להם את סיפור הפרצוף הקפוא, שעד מהרה הופך לאמיתי. בובספוג ופטריק שומעים שהולכים לסגור את עולם הכפפה והולכים לשם לבילוי אחרון. כ' עב. (שח)"
  },
  {
    "start": 1779047100,
    "end": 1779048420,
    "name": "בובספוג 8 פרק 173",
    "description": "אנימציה. 173 סקווידוויד משכנע את בובספוג שהוא חולה במחלת התמנונים ובובספוג מפחד לעבוד בסביבתו. בובספוג נבחן בנהיגה וגורם לגברת פאף להתנפח יתר על המידה. כנקמה, היא שולחת את בובספוג לדרבי ההרס. כ' עב. (שח)"
  },
  {
    "start": 1779048420,
    "end": 1779049800,
    "name": "בובספוג 8 פרק 174",
    "description": "אנימציה. פרק 174 בובספוג מביא ממתקי חלזונות חדשים שגרי יעשה הכל על מנת להגיע אליהם. פלקטון זוכה במשחק ניחושים ומר קראב יעשה הכל כדי למנוע ממנו לאסוף את הפרס שלו. כ' עב. (שח)"
  },
  {
    "start": 1779049800,
    "end": 1779051180,
    "name": "בובספוג 8 פרק 175",
    "description": "אנימציה. 175 ספיישל לחג המולד בו כל דמויות הסדרה מדומיינות מחדש כבובות תלת מימד. פלנקטון נשבע שישיג את משאלת חג המולד - גילוי הנוסחה לקציצת הסרטן. אורח מיוחד השחקן ג'ון גודמן שידבב את סנטה. כ' עב. (שח)"
  },
  {
    "start": 1779051180,
    "end": 1779052560,
    "name": "בובספוג 7 (מתורגם) פרק 135",
    "description": "אנימציה. פרק 135 בובספוג ופטריק משחקים יותר מדי עם מכונת הזמן של איש הים ונער קסם וגורמים להווה חדש בביקיני בוטום. כ' עב' (שח)"
  },
  {
    "start": 1779052560,
    "end": 1779053940,
    "name": "בובספוג 7 (מתורגם) פרק 136",
    "description": "אנימציה. פרק 136 סקווידוויד מתערב עם בובספוג שהוא לא יכול לעבור יום שלם בלי לבכות. אחרי שריסקה את רכבה ב''סרטן הפריך'' לגב' פאף אין ברירה אלא לעבוד לצד בובספוג. כ' עב'. (שח)"
  },
  {
    "start": 1779053940,
    "end": 1779055260,
    "name": "בובספוג 7 (מתורגם) פרק 137",
    "description": "אנימציה. פרק 137 מר קראב מגלה את הפחד הגדול של פלנקטון - לווייתנים. גרי מתאהב ויעשה הכל כדי להשיג את אהובת ליבו. כ' עב'. (שח)"
  },
  {
    "start": 1779055260,
    "end": 1779056640,
    "name": "בובספוג 7 (מתורגם) פרק 138",
    "description": "אנימציה. פרק 138 סקווידוויד מנסה להעלות מחזה בסרטן הפריך. סנדי עוזבת לתחרות רודיאו בטקסס ובובספוג נחוש להציל אותה. כ' עב'. (שח)"
  },
  {
    "start": 1779056640,
    "end": 1779057960,
    "name": "בובספוג 7 (מתורגם) פרק 139",
    "description": "אנימציה. פרק 139 פלנקטון מתחזה למר קראב כדי לגנוב את המתכון הסודי. מר קראב מגלה שגרי הוא מגנט מטבעות ומנצל אותו כמה שרק אפשר. כ' עב' (שח)"
  },
  {
    "start": 1779057960,
    "end": 1779059340,
    "name": "בובספוג 7 (מתורגם) פרק 140",
    "description": "אנימציה. פרק 140 פטריק מתחבר עם מפלצת-ים שהורסת דברים. בנות הים לוקחות דברים מביקיני בוטום, כולל את בובספוג וחבריו. כ' עב' (שח)"
  },
  {
    "start": 1779059340,
    "end": 1779060660,
    "name": "בובספוג 7 (מתורגם) פרק 141",
    "description": "אנימציה. פרק 141 אישה זקנה כועסת שלא קיבלה שירות בסרטן הפריך ומטילה על המקום קללה. פטריק ובובספוג הולכים למצוא את פתח הניקוז הראשי שבמרכז האוקיינוס. כ' עב' (שח)"
  },
  {
    "start": 1779060660,
    "end": 1779062040,
    "name": "בובספוג 4 (מתורגם) פרק 70",
    "description": "אנימציה. פרק 70 שלושת הבוסים השימפנזים של סנדי מגיעים לביקור פיקוח כדי לבדוק כיצד מתקדם המחקר שלה, בו השקיעו כסף. סנדי נלחצת כיוון שלא הצליחה להמציא שום דבר חדש. בובספוג ופטריק מתגייסים לעזרתה. כ' עב (שח)"
  },
  {
    "start": 1779062040,
    "end": 1779063360,
    "name": "בובספוג 4 (מתורגם) פרק 71",
    "description": "אנימציה. פרק 71 פרל חוגגת את יום הולדתה ה-16 ומר קראב חייב לעשות הכל כדי שהמסיבה תהיה מושלמת. בובספוג מקבל מברק ובו נאמר כי הוא מלך הקראטה. סנדי חושבת שמשהו חשוד ויוצאת איתו לטקס ההכתרה. כ' עב'. (שח)"
  },
  {
    "start": 1779063360,
    "end": 1779064740,
    "name": "בובספוג 4 (מתורגם) פרק 72",
    "description": "אנימציה. פרק 72 המרית של בובספוג נשברת ובזמן שהישנה שוכבת לה בבית החולים עליו להחליט אם לקנות חדשה. בובספוג חופר משאלות עבור מר קראב כדי להכניס עוד כסף. כ' עב'. (שח)"
  },
  {
    "start": 1779064740,
    "end": 1779066060,
    "name": "בובספוג 4 (מתורגם) פרק 73",
    "description": "אנימציה. פרק 73 פלנקטון מחליט לפתוח חנות מזכרות ולהפסיק לרדוף אחרי המתכון הסודי אך מר קראב לא מאמין לו. גרי נושך את סקווידוויד ולאחר שמתברר שלא קיבל חיסון, יש חשש למגיפה. כ' עב'. (שח)"
  },
  {
    "start": 1779066060,
    "end": 1779067380,
    "name": "בובספוג 3 (מתורגם) פרק 43",
    "description": "בובספוג נדהם לגלות שסקווידוורד מעולם לא טעם קציצת סרטן. הוא מצליח לשכנע אותו לקחת ביס אחד וסקווידוורד מגלה להפתעתו שזה טעים מאוד. הוא לא מודה בכך בפני בובספוג אבל אחר כך מנסה להשיג קציצה נוספת. (שח)"
  },
  {
    "start": 1779067380,
    "end": 1779068820,
    "name": "בובספוג 3 (מתורגם) פרק 44",
    "description": "מפקח בריאות מגיע ל''סרטן הפריך'' ובובספוג ומר קראב מנסים לרצות אותו. כשהם חושבים שמדובר במתחזה הם מחליטים להתנכל לו והם מכינים לו קציצה מסריחה במיוחד שחונקת אותו. (שח)"
  },
  {
    "start": 1779068820,
    "end": 1779070140,
    "name": "בובספוג 3 (מתורגם) פרק 45",
    "description": "כשאיש הים ונער הקסם נמלטים מפני בובספוג, איש הים מפיל את החגורה שלו. בובספוג המאושר לוקח אותה ומצליח לכווץ דברים אבל מגלה שאינו יודע איך להחזיר אותם לגודלם. (שח)"
  },
  {
    "start": 1779070140,
    "end": 1779071520,
    "name": "בובספוג 1 (מתורגם) פרק 3",
    "description": "מצויר. פרק 3 בובספוג ופטריק מזמינים את מר תמנון לצאת לדיג מדוזות. כשנדמה שהמצב לא יכול להיות גרוע יותר, זה בדיוק מה שקורה ופלנקטון מנסה לגנוב את הנוסחה הסודית של קציצת הסרטן. כ' עב'. (שח)"
  },
  {
    "start": 1779071520,
    "end": 1779073200,
    "name": "בובספוג 1 (מתורגם) פרק 4",
    "description": "אנימציה. פרק 4 סקווידוויד מצליח לסכסך בין בובספוג לפטריק אך מצטער על כך כשכל אחד מהם מכריז שהוא החבר הכי טוב שלו. בובספוג מנסה להשיג רישיון נהיגה בסירה ופטריק מתנדב לעזור. כ' עב'. (שח)"
  },
  {
    "start": 1779073200,
    "end": 1779074640,
    "name": "נעלמים 2 פרק 63",
    "description": "נוער. פרק 63. הטוסטמן הגיע! כרמלה מפילה על שירה סרט תדמית, ולאמה יש הצעה מפתיעה. (שח)"
  },
  {
    "start": 1779074640,
    "end": 1779076140,
    "name": "נעלמים 2 פרק 64",
    "description": "נוער. פרק 64. מה מגעיל בשערות חלבה? האם אפשר להזמין חלומות? ומה הקשר בין דייויד בואי ליעקובסון? (שח)"
  },
  {
    "start": 1779076140,
    "end": 1779077520,
    "name": "הסוכן פרק 11",
    "description": "רזי סוף סוף מצליח להפוך את קים להצלחה בינלאומית, אך רק במדינה מוזרה בשם דגסטן, שנציגה מתגלה כאיש מוזר במיוחד. כתבה על קים כמעט וחושפת את הסוד הגדול שלה. אורחת דנה גרוצקי. כ' עב'. (שח)"
  },
  {
    "start": 1779077520,
    "end": 1779079080,
    "name": "הסוכן פרק 12",
    "description": "ריאיון איום של קים מוביל לכעסים בין כולם. רגע לפני פיצוץ שמוביל לפירוק הסוכנות, רזי עולה על רעיון מבריק - יום גיבוש שיאחד בין כולם. דודי מנסה למצוא תחביב חדש ונסחף במערכת של שקרים. כ' עב'. (שח)"
  },
  {
    "start": 1779079080,
    "end": 1779080460,
    "name": "אבא מטפלת 4 פרק 13",
    "description": "לילי עוזרת לאלינור לייצר תוכנית טלוויזיה עבור דופק. הבעיה היא שלשתיים אין כשרון גדול מדי לנושא. במקביל אמרי מאבד את קמע קבוצת הכדורסל ונחרד מחוסר המזל הצפוי. (שח)"
  },
  {
    "start": 1779080460,
    "end": 1779081960,
    "name": "אבא מטפלת 4 פרק 14",
    "description": "''ליאור נרעש לגלות שהולך להיות להם אח נוסף במשפחה! הבעיה היא שהוא שכח איך להיות אבא לגיל הרך. ולילי והילדים יוצאים למסע אימונים להכשרתו. במקביל אמרי וגבי מחליפים מקומות עבודה וסוף סוף מוצאים את ייעודם. (שח)"
  },
  {
    "start": 1779081960,
    "end": 1779083460,
    "name": "צייר המערות, חדש! פרק 13",
    "description": "אובו עצוב בגלל הפרידה מבלוטה, ולרינגו יש רעיון שיכול להוציא אותו מהבאסה. בבה מגלה את הסוד של בוגה - שהיא ציידת מעולה, ובוגה מגלה את הסוד של בבה. מה הסוד שלו? תיראו-תדעו. כ' עב'. (שח)"
  },
  {
    "start": 1779083460,
    "end": 1779085020,
    "name": "צייר המערות, חדש! פרק 14",
    "description": "מישהו מהשבט מגלה שאובו הצייר! מי? לא מגלה. ואם אתם כבר יודעים - בלי ספויילרים! אובו מגלה שהוא יכול להרוויח מהציורים, ויוהו מגלה שלספר סיפורים לילדים זה מסובך. כ' עב' (שח)"
  },
  {
    "start": 1779085020,
    "end": 1779086460,
    "name": "יונייטד היי פרק 15",
    "description": "דני חושפת בפני רפאל את זהותה האמיתית. רודריגו נשבה שוב בקסמו של עומר. השגריר זועם על ליה שפגעה ביחסים הדיפלומטיים של ישראל. ניקול מגלה שאמא שלה בצרות כלכליות. כ' עב'. (שח)"
  },
  {
    "start": 1779086460,
    "end": 1779088020,
    "name": "יונייטד היי פרק 16",
    "description": "חיו של רפאל בסכנה וההצלה מגיעה מכיוון לא צפוי. עלמה מגלה עם מי לירז משתפת פעולה. נסיונה של ליה לעזור לאביה משיג את ההפך. ניקול מחפשת דרך להציל את העסקים של אמא שלה. האם בכל זאת יש סיכוי לדני ורפאל? (שח)"
  },
  {
    "start": 1779088020,
    "end": 1779089460,
    "name": "ספיידרז 2 פרק 57",
    "description": "הפישרים ניצבים פנים אל פנים מול ארנסטו. דניאל מאפשר למיה ומרקו לחפור במערה ללא רשות מאחורי גבה של אנה. דיוויד עומד לדווח לשרה על כשלון המשימה. כ' עב'. (שח)"
  },
  {
    "start": 1779089460,
    "end": 1779090900,
    "name": "ספיידרז 2 פרק 58",
    "description": "הפישרים מוצאים דרך להערים על ארנסטו בעזרתו של ליאם. ניקי ושון נשלחים להכין מפה מזויפת של המערה. טומי נותן לליאם שיעורי משחק כדי שארנסטו יאמין לסיפור שלו. כ' עב'. (שח)"
  },
  {
    "start": 1779090900,
    "end": 1779092460,
    "name": "פול ספיד 2, חדש! פרק 4",
    "description": "החבורה נשארת לעזור לנמרוד. עומר נקרעת בין מחנה האימונים בוולנסיה לחבריה ולמייקי. עמליה מתאכזבת מהיחסשל מאור. קרלוס עוזר לנועה ותופס את תשומת ליבה. מאור מקבל הצעה מסתורית מפדרו. כ' עב'. (שח)"
  },
  {
    "start": 1779092460,
    "end": 1779094020,
    "name": "פול ספיד 2, חדש! פרק 5",
    "description": "החבורה מארגנת מסיבת רוכבים. עמליה בוחנת את רגשותיו של מאור, ומייקי מנסה להסתיר את כאביו. כרמן עוזרת לו, מה שמעורר את חשדה של עומר. *הסדרה מכילה תכנים רגישים הקשורים בהתמכרויות במטרה להעלות מודעות. (שח)"
  },
  {
    "start": 1779094020,
    "end": 1779095520,
    "name": "אבא מטפלת פרק 14",
    "description": "דווקא ביום בו ליאור אמור לגלם את התפקיד הראשי בהצגה ''חלום ליל קיץ'' אייל ולילי מחליטים לקחת אחריות ולנסות לשדך בין שקד, מה שמוביל לשרשרת אי הבנות, קנאות, תככים ואהבות נסתרות. (שח)"
  },
  {
    "start": 1779095520,
    "end": 1779097020,
    "name": "אבא מטפלת פרק 15",
    "description": "ליאור נעזר בלילי כדי לעשות טקס חידוש נדרים בהפתעה למיקי אהובת ליבו. אלא שחמוטל ומיקי חושדות שמשהו אחר קורה בבית, הרבה יותר מפחיד מחידוש נדרים... במקביל שיר ששקד כתבה לאורי מצליח קצת יותר מדי... (שח)"
  },
  {
    "start": 1779097020,
    "end": 1779098580,
    "name": "יונייטד היי פרק 3",
    "description": "רפאל ולואי מנסים להשתלב ביונייטד. רודריגו רוצה לעזור לרותם להתקרב לוונסה. לואי מארגן מסיבה לכל הכיתה. הסוד של ניקול מתגלה בניגוד לרצונה. מה יקרה כשהחבילה החשודה תגיע לידיים של ונסה? כ' עב'. (שח)"
  },
  {
    "start": 1779098580,
    "end": 1779100080,
    "name": "יונייטד היי פרק 4",
    "description": "אחרי שנשלח אליה דובי ממולכד, ונסה מודיעה שהיא עוזבת את בית הספר וחוזרת לקנדה. לואי משפיל את ניקול לפני כולם, והיא בתגובה מחזירה מלחמה. ליה מסולקת ע''י עלמה מבית הספר, ומניחה שדני תעזוב יחד איתה. כ' עב' (שח)"
  },
  {
    "start": 1779100080,
    "end": 1779101760,
    "name": "קווסט פרק 12",
    "description": "אבשה מלקק את פצעיו ובטוח שהכל אבוד עד שמגלה פרט חדש ומעניין על המכרה. סדקים ראשונים מופיעים בקשר של מאי וצליל, וגורי מקבל סימן מלמעלה שאולי הקיץ הזה יותר גורלי ממה שחשב. כ' עב'. (שח)"
  },
  {
    "start": 1779101760,
    "end": 1779103200,
    "name": "קווסט פרק 13",
    "description": "גאיה מחליטה לעזוב את האי ולחפש את אמא שלה, אבל תגלית מטלטלת משאירה אותה. אבשה חוקר את הגבישים מהמכרה ומבין שהסיפור רק הולך ומסתבך. נגה מתלבטת אם לגלות לאדם את האמת. כ' עב'. (שח)"
  },
  {
    "start": 1779103200,
    "end": 1779104640,
    "name": "נעלמים 3 פרק 25",
    "description": "נוער. פרק 25. (שח)"
  },
  {
    "start": 1779104640,
    "end": 1779106140,
    "name": "נעלמים 3 פרק 26",
    "description": "נוער. פרק 26. (שח)"
  },
  {
    "start": 1779106140,
    "end": 1779107640,
    "name": "פול ספיד 2, חדש! פרק 18",
    "description": "החבורה מגלה מי גנב את הכסף. האם יספיקו להציל את נמרוד לפני שיהיה מאוחר מדי? ההרפתקה הבלתי נשכחת מגיעה לסיום עוצר נשימה. *הסדרה מכילה תכנים רגישים הקשורים בהתמכרויות במטרה להעלות מודעות לנושא זה. כ' עב (שח)"
  },
  {
    "start": 1779107640,
    "end": 1779109080,
    "name": "פול ספיד 2, חדש! פרק 19",
    "description": "בואו לגלות את הסודות של פול ספיד 2 - פעלולנים, אתרי צילום, מתיחות וצחוקים מאחורי דרמת האקשן הכי מותחת על המסך. *הסדרה מכילה תכנים רגישים הקשורים בהתמכרויות, במטרה להעלות מודעות לנושא זה. כ' עב'. (שח)"
  },
  {
    "start": 1779109080,
    "end": 1779110400,
    "name": "אבא מטפלת 6 פרק 7",
    "description": "לילי עוזרת לאלינור להתפרנס בפעם הראשונה בחייה בדרכים שרק לילי יודעת לעזור. גבי מתגלה כאחת מבכירות צה''ל בכל הזמנים. (אורח חן מזרחי). כ' עב' (שח)"
  },
  {
    "start": 1779110400,
    "end": 1779111900,
    "name": "אבא מטפלת 6 פרק 8",
    "description": "לילי ממציאה את השקר המוגזם בהיסטוריה כדי לנצח באליפות ישראל בג'ודו. מיקי ובר מחליטות להיפרד ונשארות ביחד מסיבה מפתיעה. כ' עב'. (שח)"
  },
  {
    "start": 1779111900,
    "end": 1779113400,
    "name": "יונייטד היי",
    "description": "לבנה נקש מנסה בכל דרך להגיע אל ליבה של ניקול. נסיך מונקו מגלה שהבן שלו מאוהב בילדה ישראלית בשם דני והוא זועם. רותם מקבל מעלמה הצעה שאי אפשר לסרב לה. כ' עב'. (שח)"
  },
  {
    "start": 1779113400,
    "end": 1779114960,
    "name": "יונייטד היי פרק 14",
    "description": "ניקול עומדת מול אמא שלה. עומר מגיע לפגוש את רודריגו ומנצל אותו. ונסה חוזרת, אבל לא כולם שמחים. עלמה שולחת את רותם למשימה חדשה. דני נשברת כשהיא מגלה את השקר הגדול, ואת העובדה שהיא עומדת לשלם את המחיר. (שח)"
  },
  {
    "start": 1779114960,
    "end": 1779116460,
    "name": "פול ספיד 2, חדש! פרק 1",
    "description": "חופשת הקיץ מתחילה ונמרוד מזמין את החבורה למלון שקנה בספרד. עומר מוזמנת למחנה יוקרתי, מייקי פוגש מלצרית מקומית, ומאור מתקרב לעמליה עד שדמות מסתורית חודרת בחשאי למלון. כ' עב'. (שח)"
  },
  {
    "start": 1779116460,
    "end": 1779117840,
    "name": "פול ספיד 2, חדש! פרק 2",
    "description": "הדמות המסתורית חומקת ברגע האחרון. נמרוד נחרד כשפושע מקומי מופיע, ועומר מגלה סוד שמייקי מסתיר. החבורה חוגגת בבריכה עד שחבורת פושעים גורמת לנזק לאופנועים ומאיימת על נמרוד. כ' עב'. (שח)"
  },
  {
    "start": 1779117840,
    "end": 1779119460,
    "name": "אבא מטפלת פרק 1",
    "description": "אייל (בגילומו של יובל סמו), אבא חד הורי לוזר ומובטל, מצליח איכשהו להרוס גם את מתנת בת המצווה המושלמת שהכין לבתו. בהברקה של רגע הוא מצליח למצוא עבודה מפתיעה במיוחד כדי לחסוך כסף למתנה חדשה... שס''י (שח)"
  },
  {
    "start": 1779119460,
    "end": 1779120900,
    "name": "אבא מטפלת פרק 2",
    "description": "היום הראשון של לילי בעבודה נראה כמו המשימה הקלה בעולם, אלא שאייל מגלה שהמשימה לא פשוטה בכלל. במיוחד כאשר האנשים שהוא עובד אצלם הם משפחת דנינו-מינאז' הלא ממש שפויה... שס''י (שח)"
  },
  {
    "start": 1779120900,
    "end": 1779122340,
    "name": "ספיידרז",
    "description": "דניאל נרגש לקראת הדייט עם סופי. ניקי יוצאת לחתור עם שון. גודמן נלחץ מביקורו של מפקד אקו בטכנוסק. אנה ונוח מגלים איפה בן קלוגר ומזעיקים את הילדים לעזרה ברגע הכי פחות מתאים. (שח)"
  },
  {
    "start": 1779122340,
    "end": 1779123780,
    "name": "ספיידרז",
    "description": "הפישרים מסתבכים במהלך מבצע המעצר של בן קלוגר שמתרחש בפארק ציבורי. גודמן מודאג מהחקירה שזומן אליה באקו ומספר למשפחתו שהוא צריך לטוס לחו''ל. הספיידרז יוצאים עם הוריהם למארב לילי. (שח)"
  },
  {
    "start": 1779123780,
    "end": 1779125400,
    "name": "אבא מטפלת - שפת הסימנים פרק 31",
    "description": "''קומדיה. עלילת הסדרה עוקבת אחר אייל מנסיני, אב לבת יחידה, שקד, שנאלץ לקטוע את שגרת הבטלה שלו לאחר שידו אינה משגת לקנות לה מתנת יום הולדת. בגיל 40 הוא מחליט למצוא עבודה ולשם כך ממציא את עצמו מחדש. (שח)"
  },
  {
    "start": 1779125400,
    "end": 1779127080,
    "name": "פוראבר פרק 17",
    "description": "דרמה מוסיקלית. ד''ר בתיה גילמן לא מאמינה שזה קורה לה. אדם לא מבין בשביל מה בכלל בתיה המציאה את ההמצאה שלה. אדם ויולי מנחמים את רומי ומחליטים שהם צריכים לטפל במצב. סטיבן מחליט להפעיל את התא בעצמו. כ' עב (שח)"
  },
  {
    "start": 1779127080,
    "end": 1779128640,
    "name": "פוראבר פרק 18",
    "description": "דרמה מוסיקלית. משפחת גילמן הולכת לטיפול זוגי ומשפחתי אצל פסיכולוג. סטיבן מבקש את עזרתה של בתיה. התוכנית ''כוכב אירופה'' יוצאת לדרך, להקת סטאר נינג'ה עולה לאודישן - וגל גדות זוכה להפתעה מההפקה. כ' עב. (שח)"
  },
  {
    "start": 1779128640,
    "end": 1779129720,
    "name": "בצפר פרק 5",
    "description": "5. אביגיל המזכירה מנסה לגייס כסף על מנת להציל את המסע לפולין שבוטל בגלל בעיות תקציב. מיילי מספר לארקדי על מיזם הכובעסדה. (שח)"
  },
  {
    "start": 1779129720,
    "end": 1779130800,
    "name": "בצפר פרק 6",
    "description": "אביבה קונה מערכת כריזה לקפיטריה, גלית המחנכת ממתינה לשקט בכיתה, אביטל מספרת ליהלומה המורה לאומנות על asmr וסמדר המורה לספורט מלמדת שיעור עידוד. כ' עב. (שח)"
  },
  {
    "start": 1779130800,
    "end": 1779132120,
    "name": "בובספוג 8 - 172. פרצוף קפוא/עולם הכפפה ז''ל פרק 172",
    "description": "אנימציה. פרק 172 בובספוג ופטריק עושים פרצופים ומר קראב מספר להם את סיפור הפרצוף הקפוא, שעד מהרה הופך לאמיתי. בובספוג ופטריק שומעים שהולכים לסגור את עולם הכפפה והולכים לשם לבילוי אחרון. כ' עב. (שח)"
  },
  {
    "start": 1779132120,
    "end": 1779133500,
    "name": "בובספוג 8 פרק 173",
    "description": "אנימציה. 173 סקווידוויד משכנע את בובספוג שהוא חולה במחלת התמנונים ובובספוג מפחד לעבוד בסביבתו. בובספוג נבחן בנהיגה וגורם לגברת פאף להתנפח יתר על המידה. כנקמה, היא שולחת את בובספוג לדרבי ההרס. כ' עב. (שח)"
  },
  {
    "start": 1779133500,
    "end": 1779134820,
    "name": "בובספוג 8 פרק 174",
    "description": "אנימציה. פרק 174 בובספוג מביא ממתקי חלזונות חדשים שגרי יעשה הכל על מנת להגיע אליהם. פלקטון זוכה במשחק ניחושים ומר קראב יעשה הכל כדי למנוע ממנו לאסוף את הפרס שלו. כ' עב. (שח)"
  },
  {
    "start": 1779134820,
    "end": 1779136200,
    "name": "בובספוג 8 פרק 175",
    "description": "אנימציה. 175 ספיישל לחג המולד בו כל דמויות הסדרה מדומיינות מחדש כבובות תלת מימד. פלנקטון נשבע שישיג את משאלת חג המולד - גילוי הנוסחה לקציצת הסרטן. אורח מיוחד השחקן ג'ון גודמן שידבב את סנטה. כ' עב. (שח)"
  },
  {
    "start": 1779136200,
    "end": 1779137580,
    "name": "בובספוג 8 פרק 176",
    "description": "אנימציה. פרק 176 בובספוג מציע לפלנקטון העצוב לחפש חברים חדשים. הוא מוצא חבר חדש שבעזרתו הוא מנסה להשתלט על הסרטן הפריך. סקווידוויד לא מרגיש מוערך מספיק ועובר לעבוד במסעדת הדלי. כ' עב. (שח)"
  },
  {
    "start": 1779137580,
    "end": 1779138900,
    "name": "בובספוג 7 (מתורגם) פרק 136",
    "description": "אנימציה. פרק 136 סקווידוויד מתערב עם בובספוג שהוא לא יכול לעבור יום שלם בלי לבכות. אחרי שריסקה את רכבה ב''סרטן הפריך'' לגב' פאף אין ברירה אלא לעבוד לצד בובספוג. כ' עב'. (שח)"
  },
  {
    "start": 1779138900,
    "end": 1779140280,
    "name": "בובספוג 7 (מתורגם) פרק 137",
    "description": "אנימציה. פרק 137 מר קראב מגלה את הפחד הגדול של פלנקטון - לווייתנים. גרי מתאהב ויעשה הכל כדי להשיג את אהובת ליבו. כ' עב'. (שח)"
  },
  {
    "start": 1779140280,
    "end": 1779141600,
    "name": "בובספוג 7 (מתורגם) פרק 138",
    "description": "אנימציה. פרק 138 סקווידוויד מנסה להעלות מחזה בסרטן הפריך. סנדי עוזבת לתחרות רודיאו בטקסס ובובספוג נחוש להציל אותה. כ' עב'. (שח)"
  },
  {
    "start": 1779141600,
    "end": 1779142980,
    "name": "בובספוג 7 (מתורגם) פרק 139",
    "description": "אנימציה. פרק 139 פלנקטון מתחזה למר קראב כדי לגנוב את המתכון הסודי. מר קראב מגלה שגרי הוא מגנט מטבעות ומנצל אותו כמה שרק אפשר. כ' עב' (שח)"
  },
  {
    "start": 1779142980,
    "end": 1779144300,
    "name": "בובספוג 7 (מתורגם) פרק 140",
    "description": "אנימציה. פרק 140 פטריק מתחבר עם מפלצת-ים שהורסת דברים. בנות הים לוקחות דברים מביקיני בוטום, כולל את בובספוג וחבריו. כ' עב' (שח)"
  },
  {
    "start": 1779144300,
    "end": 1779145680,
    "name": "בובספוג 7 (מתורגם) פרק 141",
    "description": "אנימציה. פרק 141 אישה זקנה כועסת שלא קיבלה שירות בסרטן הפריך ומטילה על המקום קללה. פטריק ובובספוג הולכים למצוא את פתח הניקוז הראשי שבמרכז האוקיינוס. כ' עב' (שח)"
  },
  {
    "start": 1779145680,
    "end": 1779147000,
    "name": "בובספוג 7 (מתורגם) פרק 142",
    "description": "אנימציה. פרק 142 בובספוג ופטריק נתקלים בשבט של כפריים שלא מוכן לתת להם ללכת. סקווידוויד לא אסיר תודה על כך שהוא חי, אך כשהר הגעש של ביקיני בוטום מתפרץ הוא משנה את דעתו. כ' עב' (שח)"
  },
  {
    "start": 1779147000,
    "end": 1779148380,
    "name": "בובספוג 4 (מתורגם) פרק 71",
    "description": "אנימציה. פרק 71 פרל חוגגת את יום הולדתה ה-16 ומר קראב חייב לעשות הכל כדי שהמסיבה תהיה מושלמת. בובספוג מקבל מברק ובו נאמר כי הוא מלך הקראטה. סנדי חושבת שמשהו חשוד ויוצאת איתו לטקס ההכתרה. כ' עב'. (שח)"
  },
  {
    "start": 1779148380,
    "end": 1779149700,
    "name": "בובספוג 4 (מתורגם) פרק 72",
    "description": "אנימציה. פרק 72 המרית של בובספוג נשברת ובזמן שהישנה שוכבת לה בבית החולים עליו להחליט אם לקנות חדשה. בובספוג חופר משאלות עבור מר קראב כדי להכניס עוד כסף. כ' עב'. (שח)"
  },
  {
    "start": 1779149700,
    "end": 1779151080,
    "name": "בובספוג 4 (מתורגם) פרק 73",
    "description": "אנימציה. פרק 73 פלנקטון מחליט לפתוח חנות מזכרות ולהפסיק לרדוף אחרי המתכון הסודי אך מר קראב לא מאמין לו. גרי נושך את סקווידוויד ולאחר שמתברר שלא קיבל חיסון, יש חשש למגיפה. כ' עב'. (שח)"
  },
  {
    "start": 1779151080,
    "end": 1779152400,
    "name": "בובספוג 4 (מתורגם) פרק 74",
    "description": "אנימציה. פרק 74 בובספוג חייב לנצל את ימי החופשה שלו, אחרת מר קראב יקבל קנס מאיגוד הטבחים. בובספוג מוצא פאה ומחליט לחבוש אותה, ובשל כך הוא נהפך להיות למושא ללעג בקרב אנשי ביקיני בוטום. כ' עב'. (שח)"
  },
  {
    "start": 1779152400,
    "end": 1779153780,
    "name": "בובספוג 3 (מתורגם) פרק 44",
    "description": "מפקח בריאות מגיע ל''סרטן הפריך'' ובובספוג ומר קראב מנסים לרצות אותו. כשהם חושבים שמדובר במתחזה הם מחליטים להתנכל לו והם מכינים לו קציצה מסריחה במיוחד שחונקת אותו. (שח)"
  },
  {
    "start": 1779153780,
    "end": 1779155160,
    "name": "בובספוג 3 (מתורגם) פרק 45",
    "description": "כשאיש הים ונער הקסם נמלטים מפני בובספוג, איש הים מפיל את החגורה שלו. בובספוג המאושר לוקח אותה ומצליח לכווץ דברים אבל מגלה שאינו יודע איך להחזיר אותם לגודלם. (שח)"
  },
  {
    "start": 1779155160,
    "end": 1779156540,
    "name": "בובספוג 3 (מתורגם) פרק 46",
    "description": "שלג יורד על ''ביקיני בוטם'' ובובספוג ופטריק מתחילים מיד לנהל קרב כדורי שלג. בניגוד לרצונו , סקווידוורד מוצא את עצמו מצטרף ואפילו נהנה. מר קראב אוסף חפצים מהזבל ומוכר אותם כעתיקות.כ' עב. (שח)"
  },
  {
    "start": 1779156540,
    "end": 1779157860,
    "name": "בובספוג 1 (מתורגם) פרק 4",
    "description": "אנימציה. פרק 4 סקווידוויד מצליח לסכסך בין בובספוג לפטריק אך מצטער על כך כשכל אחד מהם מכריז שהוא החבר הכי טוב שלו. בובספוג מנסה להשיג רישיון נהיגה בסירה ופטריק מתנדב לעזור. כ' עב'. (שח)"
  },
  {
    "start": 1779157860,
    "end": 1779159600,
    "name": "בובספוג 1 (מתורגם) פרק 5",
    "description": "אנימציה. פרק 5 בובספוג וסקווידוויד נשלחים להביא פיצה לביתו של לקוח, אבל הם הולכים לאיבוד בדרכם ועוברים יסורים רבים עד שמצליחים להגיע ליעדם. כ' עב'. (שח)"
  },
  {
    "start": 1779159600,
    "end": 1779161040,
    "name": "נעלמים 2 פרק 65",
    "description": "נוער. פרק 65. המכתב מתחת לספסל, מה ג'וקי עושה בזמנו החופשי ומי עובד במשתלה? (שח)"
  },
  {
    "start": 1779161040,
    "end": 1779162540,
    "name": "נעלמים 2 פרק 66",
    "description": "נוער. פרק 66. הצ'קלקה של דולב מצילה את המצב, איך משתחררים מחבל? ומי נשאר לישון? (שח)"
  },
  {
    "start": 1779162540,
    "end": 1779163920,
    "name": "הסוכן פרק 13",
    "description": "פסח מגיע ורזי מנסה לשלב את קים בהצגת פסח, אך יש בעיה - אין תפקיד נשי בסיפור ההגדה. העובדה הזו לא עוצרת את רזי והוא ממציא בשביל קים את ''הסטורי של מושית'', הגדת הפסח המוגזמת והמטופשת של השנה. כ' עב'. (שח)"
  },
  {
    "start": 1779163920,
    "end": 1779165540,
    "name": "הסוכן פרק 14",
    "description": "רגע לפני ההופעה הגדולה של השנה, רזי מחליט לעשות מהלך ולשלוח את שאני לרגל אצל דברת, אך הדבר מתברר כטעות גדולה. לסוכנות מגיע אורח מפתיע שהולך לשנות הכול. אורח עמי אניג'ר. כ' עב'. (שח)"
  },
  {
    "start": 1779165540,
    "end": 1779167100,
    "name": "אבא מטפלת 5, שפת סימנים פרק 1",
    "description": "צדי צרפתי האגדי מגלה את נציגי ישראל הבאים לאירוויזיון - משפחת דנינו מינאז' מחוזקים בלילי האגדית. הכול הולך לפי התכניות עד שגבי מגיעה ודורשת מאייל להגשים את חלומה ולהשתתף גם כן. כ' עב'. (שח)"
  },
  {
    "start": 1779167100,
    "end": 1779168480,
    "name": "אבא מטפלת 5, שפת סימנים פרק 2",
    "description": "ליאור משיג פריט אספנים יוצא דופן - הפומפה מפומפי! הבעיה היא שלילי איבדה אותו. כעת לילי והילדים יוצאים למסע מטורף אחר הפומפה האבודה, מסע שיוביל אותם לכל תחתית אפשרית. כ' עב'. (שח)"
  },
  {
    "start": 1779168480,
    "end": 1779170040,
    "name": "צייר המערות, חדש! פרק 15",
    "description": "תאמינו לי, לא מבין למה לקרוא את התקצירים האלה, במקום פשוט לראות את הפרק. הוא הרבה יותר מצחיק מהתקציר. היום נגיד אובו מנסה לבטל את יום ההורים בבית ספר. פישה. כ' עב'. (שח)"
  },
  {
    "start": 1779170040,
    "end": 1779171540,
    "name": "צייר המערות, חדש! פרק 16",
    "description": "ביף וגאזל נפרדים. שוב. מבחינת בוגה, זו הזדמנות להתקרב לביף. מבחינת אובו, זה הפחד הכי גדול שלו (אחרי עכבישים, אחרי בריונים ואחרי עוד איזה עשרים דברים). מיקה ויוהו מוצאים משחק מהילדות שלהם. כ' עב'. (שח)"
  },
  {
    "start": 1779171540,
    "end": 1779173040,
    "name": "יונייטד היי פרק 17",
    "description": "החקירה של הפריצה לחדר של ונסה וניקול מעלה יותר שאלות מתשובות. רודריגו יוצא להגנת עומר מול רותם, אבל גם הוא מתקשה להאמין לחבר הוותיק שלו. האם התוכנית של דני ורפאל תצליח, והם יוכלו להיות יחד? כ' עב'. (שח)"
  },
  {
    "start": 1779173040,
    "end": 1779174480,
    "name": "יונייטד היי פרק 18",
    "description": "פרק אחרון לעונה. ניקול משוכנעת שהטבעת תציל את אמא שלה, אבל בפועל היא מסכנת את חייה. רפאל ודני עם לב שבור. האם סיפור האהבה הבלתי אפשרי שלהם יסתיים באושר ועושר? כ' עב'. (שח)"
  },
  {
    "start": 1779174480,
    "end": 1779175920,
    "name": "ספיידרז 2 פרק 59",
    "description": "ליאם נפגש עם ארנסטו תחת מעקב צמוד של הפישרים. שון עוזב את השמורה. הפישרים מכינים מלכודת לצוות של ארנסטו, מבלי לדעת שמיה ומרקו נמצאים במערה.כ' עב'. (שח)"
  },
  {
    "start": 1779175920,
    "end": 1779177300,
    "name": "ספיידרז 2 פרק 60",
    "description": "ליאם ממתין שיחלצו אותו מדירת המחבוא. ניקי וטומי מבינים שהמצלמות במערה משדרות חומרים ישנים. דניאל אנה ונוח מגלים שהססמונטור כבר הופעל ושאין להם איך לעצור אותו.כ' עב'. (שח)"
  },
  {
    "start": 1779177300,
    "end": 1779178860,
    "name": "פול ספיד 2, חדש! פרק 6",
    "description": "מייקי סובל מכאבים במסיבה, וכרמן מציעה עזרה מפוקפקת. פדרו וקרלוס זוממים תוכנית, ועמליה מגלה סוד כשעומר מפתיעה את כולם בהגעתה. *הסדרה מכילה תכנים רגישים הקשורים בהתמכרויות, במטרה להעלות מודעות לנושא זה. (שח)"
  },
  {
    "start": 1779178860,
    "end": 1779180480,
    "name": "פול ספיד 2, חדש! פרק 7",
    "description": "מייקי מסתיר את מצבו מעומר. עמליה רוצה לדבר עם מאור על הנשיקה. קרלוס מזמין את נועה לדייט. פריגוז'ין מתכנן מהלך מסוכן להפיל את החבורה. *הסדרה מכילה תכנים רגישים הקשורים בהתמכרויות, במטרה להעלות מודעות. (שח)"
  },
  {
    "start": 1779180480,
    "end": 1779181980,
    "name": "אבא מטפלת",
    "description": "אורחת מפתיעה מגיעה עם אמה המגניבה של שקד, שכובשת את לבבותיהם של כל הסובבים ומשאירה אבק לאייל. במקביל במשפחת דנינו רוצים לחגוג את יום הולדתה של לילי, אך מגלים עליה אמיתות מרעישות. (שח)"
  },
  {
    "start": 1779181980,
    "end": 1779183600,
    "name": "אבא מטפלת פרק 17",
    "description": "אייל מגיע לשעשועון טריוויה בו יוכל לזכות במיליון שקלים! למרות שהידע הכללי שלו שואף לאפס, הוא מוצא דרך ייחודית לעלות ולטפס בשעשועון. (שח)"
  },
  {
    "start": 1779183600,
    "end": 1779185100,
    "name": "יונייטד היי פרק 5",
    "description": "רותם מקבל עצות מרודריגו איך להתחיל עם בנות ומנסה ליישם אותן. עלמה מפוטרת אבל לא מתכוונת לעזוב כל כך בקלות. דני דורשת תשובות מרפאל ולא יודעת שבזמן הזה ליה מתכננת את המהלך שיביא לסילוקה מבית הספר. כ' עב (שח)"
  },
  {
    "start": 1779185100,
    "end": 1779186720,
    "name": "יונייטד היי - 6. שחנ''ש פרק 6",
    "description": "כשהסוד על הנסיך והמאבטח שלו מתגלה, שום דבר לא נותר כשהיה. הבנות עושות שחנ''ש וניקול מגלה את האמת על רודריגו. רותם מגלה שעלמה היא לא סתם מורה. ליה מנסה להתפייס עם דני, אך כל סוד סופו להתגלות. כ' עב'. (שח)"
  },
  {
    "start": 1779186720,
    "end": 1779188220,
    "name": "קווסט פרק 14",
    "description": "האמת הגדולה נחשפת ואבשה מבין שהאשים כל הזמן את האנשים הלא נכונים. גאיה יוצאת להציל את אבשה ונתקלת במכשולים לא צפויים. נגה חושפת את מאי בפני אדם וגורי מחליט לנקום באחיו. כ' עב'. (שח)"
  },
  {
    "start": 1779188220,
    "end": 1779189660,
    "name": "קווסט פרק 15",
    "description": "גאיה משחררת את אבשה ויפתח מהמכרה אבל נתקלת בהפתעה שמשנה את הכל. גורי מוציא את תוכניתו הזדונית לפועל ומאי נתקלת בבעיה שמאיימת על ההשקה. כ' עב'. (שח)"
  },
  {
    "start": 1779189660,
    "end": 1779191100,
    "name": "נעלמים 3 פרק 27",
    "description": "אז מה היה לנו בעצם? ומי עושה קאמבק מפתיע? (שח)"
  },
  {
    "start": 1779191100,
    "end": 1779192600,
    "name": "נעלמים 3 פרק 28",
    "description": "איפה שכחו את עידו, מה צריך עכשיו מיניב, ומי הגיע פתאום לטוסטר? (שח)"
  },
  {
    "start": 1779192600,
    "end": 1779194280,
    "name": "צייר המערות, חדש! פרק 1",
    "description": "אובו, נער קדמון שאביו הוא ראש השבט, מתכונן למסע הציד הראשון שלו. האם בוגה תצליח להפוך אותו לצייד מוכשר, או שהוא יגלה דווקא כישרון אחר? וגם פו ממציאה המצאה שתשנה את חיי השבט לנצח. כ' עב'. (שח)"
  },
  {
    "start": 1779194280,
    "end": 1779195720,
    "name": "צייר המערות, חדש! פרק 2",
    "description": "בבה מוצא דרך לגלות מי הצייד כדי לגרש אותו מהשבט. אובו יעשה הכל כדי שהסוד שלו לא יתגלה, ובוגה מגלה לו את הסוד שלה. פו מתחילה ללמוד בבית הספר, ומבינה שזה לא קל כמו שהיא חשבה. כ' עב'. (שח)"
  },
  {
    "start": 1779195720,
    "end": 1779197160,
    "name": "אבא מטפלת 6 פרק 9",
    "description": "לילי עוזרת לגוני להתגבר על פחד הבמה שלה לקראת המפגש של גוני עם המרצה שלה באוניברסיטה. גבי מנצלת את מבצע ''אכול כפי יכולתך'' בדונאטסיה כמו שרק גבי יכולה. כ' עב'. (שח)"
  },
  {
    "start": 1779197160,
    "end": 1779198660,
    "name": "אבא מטפלת 6 פרק 10",
    "description": "גבי ''מרגלית'' מנסיני מגיעה למשפחת מנסיני ופותחת חזית עם גבי ''ערגלית'' מנסיני בקרב על מי היא הגבי המקורית. קובי סטאר מתקבל לתוכנית ריאליטי יוקרתית. (אורח דוד דביר) כ' עב'. (שח)"
  },
  {
    "start": 1779198660,
    "end": 1779200100,
    "name": "יונייטד היי פרק 15",
    "description": "דני חושפת בפני רפאל את זהותה האמיתית. רודריגו נשבה שוב בקסמו של עומר. השגריר זועם על ליה שפגעה ביחסים הדיפלומטיים של ישראל. ניקול מגלה שאמא שלה בצרות כלכליות. כ' עב'. (שח)"
  },
  {
    "start": 1779200100,
    "end": 1779201660,
    "name": "יונייטד היי פרק 16",
    "description": "חיו של רפאל בסכנה וההצלה מגיעה מכיוון לא צפוי. עלמה מגלה עם מי לירז משתפת פעולה. נסיונה של ליה לעזור לאביה משיג את ההפך. ניקול מחפשת דרך להציל את העסקים של אמא שלה. האם בכל זאת יש סיכוי לדני ורפאל? (שח)"
  },
  {
    "start": 1779201660,
    "end": 1779203280,
    "name": "פול ספיד 2, חדש! פרק 3",
    "description": "נמרוד מגלה למאור את הסוד שהסתיר לגבי המלון. פרגוז'ין לוחץ את נמרוד לפינה ומאור מתנדב לעזור. עמליה מנסה להתקרב למאור, ונועה מגלה שהוא הלווה את כל כספו לנמרוד. כ' עב'. (שח)"
  },
  {
    "start": 1779203280,
    "end": 1779204840,
    "name": "פול ספיד 2, חדש! פרק 4",
    "description": "החבורה נשארת לעזור לנמרוד. עומר נקרעת בין מחנה האימונים בוולנסיה לחבריה ולמייקי. עמליה מתאכזבת מהיחסשל מאור. קרלוס עוזר לנועה ותופס את תשומת ליבה. מאור מקבל הצעה מסתורית מפדרו. כ' עב'. (שח)"
  },
  {
    "start": 1779204840,
    "end": 1779206460,
    "name": "אבא מטפלת פרק 4",
    "description": "4. ליאור בלחץ גדול בעקבות בואו של ליעוז אחיו המוצלח והנערץ. לילי מציעה שליאור יציג משפחה לתפארת לקנאתו של ליעוז, אלא שהיא לא לוקחת בחשבון שתי עובדות המשפחה לא מושלמת וליעוז מכיר את אייל מעברו... שס''י (שח)"
  },
  {
    "start": 1779206460,
    "end": 1779208140,
    "name": "אבא מטפלת פרק 5",
    "description": "5. אייל מגלה לתדהמתו שיום הבריכה המסורתי בבית הספר של שקד בוטל בגלל חמוטל אמא של קלואי ויו''ר ועד ההורים. בעזרת לילי, יועצת הסתרים של חמוטל, הוא יוצא למסע בחירות מלוכלך וחסר רחמים. שס''י (שח)"
  },
  {
    "start": 1779208140,
    "end": 1779209580,
    "name": "ספיידרז פרק 9",
    "description": "בן מגלה לפישרים איפה הבלו בירד. גודמן מבריז מהחקירה באקו, וניקי נשלחת בלית ברירה להוציא משון איפה הוא. לדניאל יש מתחרה על לבה של סופי. אנה והבנים נוסעים להאנגר נטוש להביא את הבלו בירד. (שח)"
  },
  {
    "start": 1779209580,
    "end": 1779211020,
    "name": "ספיידרז פרק 10",
    "description": "אנה והבנים מגלים שהבלו בירד נעלמה. שון וחבריו לנבחרת מדווחים למועצה על מצב המים באגם. ניקי ממשיכה לתחקר את שון על גודמן, אך יש לה נקיפות מצפון. לין, האקסית של שון, רואה אותם ביחד ומקנאה. (שח)"
  },
  {
    "start": 1779211020,
    "end": 1779212520,
    "name": "אבא מטפלת - שפת הסימנים פרק 32",
    "description": "''קומדיה. עלילת הסדרה עוקבת אחר אייל מנסיני, אב לבת יחידה, שקד, שנאלץ לקטוע את שגרת הבטלה שלו לאחר שידו אינה משגת לקנות לה מתנת יום הולדת. בגיל 40 הוא מחליט למצוא עבודה ולשם כך ממציא את עצמו מחדש. (שח)"
  },
  {
    "start": 1779212520,
    "end": 1779214080,
    "name": "פוראבר פרק 19",
    "description": "אורנה דץ מפתיעה את נבחרת הכוכב הבא ומוציאה לדרך את משימת הלילה הלבן - המתמודדים יחולקו לזוגות ויעבדו כל הלילה עד לאודישן בשידור חי בבוקר. דודו מתקשה להתמודד עם המצב והעניינים רק הולכים ומידרדרים. כ' ע (שח)"
  },
  {
    "start": 1779214080,
    "end": 1779215760,
    "name": "פוראבר פרק 20",
    "description": "המפיקה לימור מרוצה מהדרמה הגדולה בין גל, בת-אל ועומר ששודרה בשידור חי. רומי ויולי מגיעות במהירות לאולפנים. הקטור כועס על סטיבן. משימת הלילה הלבן מסתיימת והמתמודדים מבצעים דואטים בשידור חי. כ' עב. (שח)"
  },
  {
    "start": 1779215760,
    "end": 1779216840,
    "name": "בצפר פרק 6",
    "description": "אביבה קונה מערכת כריזה לקפיטריה, גלית המחנכת ממתינה לשקט בכיתה, אביטל מספרת ליהלומה המורה לאומנות על asmr וסמדר המורה לספורט מלמדת שיעור עידוד. כ' עב. (שח)"
  },
  {
    "start": 1779216840,
    "end": 1779218160,
    "name": "בובספוג 8 פרק 173",
    "description": "אנימציה. 173 סקווידוויד משכנע את בובספוג שהוא חולה במחלת התמנונים ובובספוג מפחד לעבוד בסביבתו. בובספוג נבחן בנהיגה וגורם לגברת פאף להתנפח יתר על המידה. כנקמה, היא שולחת את בובספוג לדרבי ההרס. כ' עב. (שח)"
  },
  {
    "start": 1779218160,
    "end": 1779219540,
    "name": "בובספוג 8 פרק 174",
    "description": "אנימציה. פרק 174 בובספוג מביא ממתקי חלזונות חדשים שגרי יעשה הכל על מנת להגיע אליהם. פלקטון זוכה במשחק ניחושים ומר קראב יעשה הכל כדי למנוע ממנו לאסוף את הפרס שלו. כ' עב. (שח)"
  },
  {
    "start": 1779219540,
    "end": 1779220920,
    "name": "בובספוג 8 פרק 175",
    "description": "אנימציה. 175 ספיישל לחג המולד בו כל דמויות הסדרה מדומיינות מחדש כבובות תלת מימד. פלנקטון נשבע שישיג את משאלת חג המולד - גילוי הנוסחה לקציצת הסרטן. אורח מיוחד השחקן ג'ון גודמן שידבב את סנטה. כ' עב. (שח)"
  },
  {
    "start": 1779220920,
    "end": 1779222300,
    "name": "בובספוג 8 פרק 176",
    "description": "אנימציה. פרק 176 בובספוג מציע לפלנקטון העצוב לחפש חברים חדשים. הוא מוצא חבר חדש שבעזרתו הוא מנסה להשתלט על הסרטן הפריך. סקווידוויד לא מרגיש מוערך מספיק ועובר לעבוד במסעדת הדלי. כ' עב. (שח)"
  },
  {
    "start": 1779222300,
    "end": 1779223620,
    "name": "בובספוג 8 פרק 177",
    "description": "אנימציה. פרק 177 פקח עירייה מגיע אל הסרטן הפריך ומסעדת הדלי כדי לעדכן אותם בתקנה חדשה המדאיגה את שני הצדדים. כ' עב. (שח)"
  },
  {
    "start": 1779223620,
    "end": 1779225000,
    "name": "בובספוג 7 (מתורגם) פרק 137",
    "description": "אנימציה. פרק 137 מר קראב מגלה את הפחד הגדול של פלנקטון - לווייתנים. גרי מתאהב ויעשה הכל כדי להשיג את אהובת ליבו. כ' עב'. (שח)"
  },
  {
    "start": 1779225000,
    "end": 1779226320,
    "name": "בובספוג 7 (מתורגם) פרק 138",
    "description": "אנימציה. פרק 138 סקווידוויד מנסה להעלות מחזה בסרטן הפריך. סנדי עוזבת לתחרות רודיאו בטקסס ובובספוג נחוש להציל אותה. כ' עב'. (שח)"
  },
  {
    "start": 1779226320,
    "end": 1779227700,
    "name": "בובספוג 7 (מתורגם) פרק 139",
    "description": "אנימציה. פרק 139 פלנקטון מתחזה למר קראב כדי לגנוב את המתכון הסודי. מר קראב מגלה שגרי הוא מגנט מטבעות ומנצל אותו כמה שרק אפשר. כ' עב' (שח)"
  },
  {
    "start": 1779227700,
    "end": 1779229020,
    "name": "בובספוג 7 (מתורגם) פרק 140",
    "description": "אנימציה. פרק 140 פטריק מתחבר עם מפלצת-ים שהורסת דברים. בנות הים לוקחות דברים מביקיני בוטום, כולל את בובספוג וחבריו. כ' עב' (שח)"
  },
  {
    "start": 1779229020,
    "end": 1779230400,
    "name": "בובספוג 7 (מתורגם) פרק 141",
    "description": "אנימציה. פרק 141 אישה זקנה כועסת שלא קיבלה שירות בסרטן הפריך ומטילה על המקום קללה. פטריק ובובספוג הולכים למצוא את פתח הניקוז הראשי שבמרכז האוקיינוס. כ' עב' (שח)"
  },
  {
    "start": 1779230400,
    "end": 1779231720,
    "name": "בובספוג 7 (מתורגם) פרק 142",
    "description": "אנימציה. פרק 142 בובספוג ופטריק נתקלים בשבט של כפריים שלא מוכן לתת להם ללכת. סקווידוויד לא אסיר תודה על כך שהוא חי, אך כשהר הגעש של ביקיני בוטום מתפרץ הוא משנה את דעתו. כ' עב' (שח)"
  },
  {
    "start": 1779231720,
    "end": 1779233100,
    "name": "בובספוג 7 (מתורגם) פרק 143",
    "description": "אנימציה. פרק 143 לאחר שמר קראב החביא את המתכון הסודי בצד השני של האוקיינוס, בובספוג נשלח להביא אותו ומגלה שמישהו גנב את המתכון. מי זה יכול להיות? כ' עב' (שח)"
  },
  {
    "start": 1779233100,
    "end": 1779234420,
    "name": "בובספוג 4 (מתורגם) פרק 72",
    "description": "אנימציה. פרק 72 המרית של בובספוג נשברת ובזמן שהישנה שוכבת לה בבית החולים עליו להחליט אם לקנות חדשה. בובספוג חופר משאלות עבור מר קראב כדי להכניס עוד כסף. כ' עב'. (שח)"
  },
  {
    "start": 1779234420,
    "end": 1779235800,
    "name": "בובספוג 4 (מתורגם) פרק 73",
    "description": "אנימציה. פרק 73 פלנקטון מחליט לפתוח חנות מזכרות ולהפסיק לרדוף אחרי המתכון הסודי אך מר קראב לא מאמין לו. גרי נושך את סקווידוויד ולאחר שמתברר שלא קיבל חיסון, יש חשש למגיפה. כ' עב'. (שח)"
  }
]
